sparksqlformatter/__init__.py
sparksqlformatter/__main__.py
sparksqlformatter/src/__init__.py
sparksqlformatter/src/api.py
sparksqlformatter/src/config.py
sparksqlformatter/src/formatter.py
sparksqlformatter/src/indentation.py
sparksqlformatter/src/inline_block.py
sparksqlformatter/src/style.py
sparksqlformatter/src/subquery.py
sparksqlformatter/src/tokenizer.py
sparksqlformatter/tests/__init__.py
sparksqlformatter/tests/sparksqlformatter_test.py
sparksqlformatter-0.1.12.dist-info/LICENSE
sparksqlformatter-0.1.12.dist-info/METADATA
sparksqlformatter-0.1.12.dist-info/WHEEL
sparksqlformatter-0.1.12.dist-info/entry_points.txt
sparksqlformatter-0.1.12.dist-info/top_level.txt
sparksqlformatter-0.1.12.dist-info/RECORD
