Metadata-Version: 2.1
Name: sparksqlformatter
Version: 0.1.12
Summary: A SparkSQL formatter in Python based on https://github.com/zeroturnaround/sql-formatter, with customizations and extra features.
Home-page: https://github.com/largecats/sparksql-formatter
Author: largecats
Author-email: linfanxiaolinda@outlook.com
License: UNKNOWN
Platform: UNKNOWN
Classifier: Programming Language :: Python
Classifier: Programming Language :: Python :: 2
Classifier: Programming Language :: Python :: 2.7
Classifier: Programming Language :: Python :: 3
Classifier: Programming Language :: Python :: 3.6
Classifier: License :: OSI Approved :: MIT License
Classifier: Operating System :: OS Independent
License-File: LICENSE
Requires-Dist: configparser
